LICENSE.md
README.md
setup.py
src/atmp/TCP.py
src/atmp/__init__.py
src/atmp/blocks.py
src/atmp/console.py
src/atmp/devices.py
src/pyatmp.egg-info/PKG-INFO
src/pyatmp.egg-info/SOURCES.txt
src/pyatmp.egg-info/dependency_links.txt
src/pyatmp.egg-info/top_level.txt