Metadata-Version: 2.1
Name: pyatmp
Version: 0.9.0
Summary: Package for interfacing with ATMP software
Home-page: UNKNOWN
Author: Sébastien Deriaz
Author-email: sebastien.deriaz1@gmail.com
License: UNKNOWN
Platform: UNKNOWN
License-File: LICENSE.md
